{
  "immersivepetroleum:recipes/immersivepetroleum/upgrade_rudders": {
    "criteria": {
      "has_the_recipe": "2023-12-29 11:19:36 +0100"
    },
    "done": true
  },
  "immersivepetroleum:recipes/immersivepetroleum/asphalt": {
    "criteria": {
      "has_the_recipe": "2023-12-29 11:19:36 +0100"
    },
    "done": true
  },
  "immersivepetroleum:recipes/building_blocks/cut_copper_stairs_paraffin_waxed": {
    "criteria": {
      "has_the_recipe": "2023-12-29 11:19:36 +0100"
    },
    "done": true
  },
  "immersivepetroleum:recipes/building_blocks/cut_copper_slab_paraffin_waxed": {
    "criteria": {
      "has_the_recipe": "2023-12-29 11:19:36 +0100"
    },
    "done": true
  },
  "immersiveengineering:recipes/immersiveengineering/crafting/redstone_acid": {
    "criteria": {
      "has_redstone_dust": "2023-12-29 11:26:50 +0100"
    },
    "done": true
  },
  "minecraft:recipes/tools/compass": {
    "criteria": {
      "has_redstone": "2023-12-29 11:26:50 +0100"
    },
    "done": true
  },
  "immersivepetroleum:recipes/building_blocks/exposed_cut_copper_stairs_paraffin_waxed": {
    "criteria": {
      "has_the_recipe": "2023-12-29 11:19:36 +0100"
    },
    "done": true
  },
  "immersiveengineering:recipes/immersiveengineering/crafting/armor_steel_legs": {
    "criteria": {
      "has_steel_plate": "2023-12-29 11:26:42 +0100"
    },
    "done": true
  },
  "immersivepetroleum:recipes/immersivepetroleum/paraffin_wax_to_block": {
    "criteria": {
      "has_the_recipe": "2023-12-29 11:19:36 +0100"
    },
    "done": true
  },
  "minecraft:recipes/redstone/target": {
    "criteria": {
      "has_redstone": "2023-12-29 11:26:50 +0100"
    },
    "done": true
  },
  "immersiveengineering:recipes/immersiveengineering/crafting/rs_engineering": {
    "criteria": {
      "has_redstone": "2023-12-29 11:26:50 +0100"
    },
    "done": true
  },
  "immersiveengineering:recipes/immersiveengineering/crafting/armor_steel_feet": {
    "criteria": {
      "has_steel_plate": "2023-12-29 11:26:42 +0100"
    },
    "done": true
  },
  "immersivepetroleum:recipes/building_blocks/weathered_copper_paraffin_waxed": {
    "criteria": {
      "has_the_recipe": "2023-12-29 11:19:36 +0100"
    },
    "done": true
  },
  "minecraft:adventure/adventuring_time": {
    "criteria": {
      "minecraft:desert": "2023-12-29 11:19:40 +0100"
    },
    "done": false
  },
  "immersivepetroleum:recipes/building_blocks/copper_block_paraffin_waxed": {
    "criteria": {
      "has_the_recipe": "2023-12-29 11:19:36 +0100"
    },
    "done": true
  },
  "immersivepetroleum:recipes/immersivepetroleum/speedboat": {
    "criteria": {
      "has_the_recipe": "2023-12-29 11:19:36 +0100"
    },
    "done": true
  },
  "immersivepetroleum:recipes/immersivepetroleum/petcoke_block_to_items": {
    "criteria": {
      "has_the_recipe": "2023-12-29 11:19:36 +0100"
    },
    "done": true
  },
  "minecraft:recipes/redstone/redstone_torch": {
    "criteria": {
      "has_redstone": "2023-12-29 11:26:50 +0100"
    },
    "done": true
  },
  "immersivepetroleum:recipes/building_blocks/oxidized_cut_copper_slab_paraffin_waxed": {
    "criteria": {
      "has_the_recipe": "2023-12-29 11:19:36 +0100"
    },
    "done": true
  },
  "immersivepetroleum:recipes/building_blocks/oxidized_cut_copper_stairs_paraffin_waxed": {
    "criteria": {
      "has_the_recipe": "2023-12-29 11:19:36 +0100"
    },
    "done": true
  },
  "immersivepetroleum:recipes/building_blocks/exposed_cut_copper_paraffin_waxed": {
    "criteria": {
      "has_the_recipe": "2023-12-29 11:19:36 +0100"
    },
    "done": true
  },
  "immersivepetroleum:recipes/building_blocks/exposed_cut_copper_slab_paraffin_waxed": {
    "criteria": {
      "has_the_recipe": "2023-12-29 11:19:36 +0100"
    },
    "done": true
  },
  "immersiveengineering:recipes/immersiveengineering/crafting/sheetmetal_steel": {
    "criteria": {
      "has_plate_steel": "2023-12-29 11:26:42 +0100"
    },
    "done": true
  },
  "immersivepetroleum:recipes/immersivepetroleum/asphalt2": {
    "criteria": {
      "has_the_recipe": "2023-12-29 11:19:36 +0100"
    },
    "done": true
  },
  "alchemistry:recipes/dissolver/bone_block": {
    "criteria": {
      "has_the_recipe": "2023-12-29 11:22:29 +0100"
    },
    "done": true
  },
  "mekanism:steel_casing": {
    "criteria": {
      "steel_casing": "2023-12-29 11:25:00 +0100"
    },
    "done": true
  },
  "minecraft:recipes/misc/white_dye": {
    "criteria": {
      "has_bone_meal": "2023-12-29 11:22:29 +0100"
    },
    "done": true
  },
  "mekanism:basic_control_circuit": {
    "criteria": {
      "basic_control_circuit": "2023-12-29 11:25:07 +0100"
    },
    "done": true
  },
  "immersivepetroleum:recipes/building_blocks/weathered_cut_copper_slab_paraffin_waxed": {
    "criteria": {
      "has_the_recipe": "2023-12-29 11:19:36 +0100"
    },
    "done": true
  },
  "immersivepetroleum:recipes/immersivepetroleum/petcoke_items_to_block": {
    "criteria": {
      "has_the_recipe": "2023-12-29 11:19:36 +0100"
    },
    "done": true
  },
  "immersivepetroleum:recipes/building_blocks/cut_copper_paraffin_waxed": {
    "criteria": {
      "has_the_recipe": "2023-12-29 11:19:36 +0100"
    },
    "done": true
  },
  "immersivepetroleum:recipes/immersivepetroleum/seismic_survey_tool": {
    "criteria": {
      "has_the_recipe": "2023-12-29 11:19:36 +0100"
    },
    "done": true
  },
  "immersiveengineering:recipes/immersiveengineering/crafting/armor_steel_chest": {
    "criteria": {
      "has_steel_plate": "2023-12-29 11:26:42 +0100"
    },
    "done": true
  },
  "farmersdelight:main/root": {
    "criteria": {
      "seeds": "2023-12-29 11:19:54 +0100"
    },
    "done": true
  },
  "immersivepetroleum:recipes/building_blocks/weathered_cut_copper_paraffin_waxed": {
    "criteria": {
      "has_the_recipe": "2023-12-29 11:19:36 +0100"
    },
    "done": true
  },
  "immersivepetroleum:recipes/immersivepetroleum/upgrade_icebreaker": {
    "criteria": {
      "has_the_recipe": "2023-12-29 11:19:36 +0100"
    },
    "done": true
  },
  "immersivepetroleum:recipes/immersivepetroleum/paraffin_wax_block_to_items": {
    "criteria": {
      "has_the_recipe": "2023-12-29 11:19:36 +0100"
    },
    "done": true
  },
  "immersivepetroleum:recipes/immersivepetroleum/asphalt_stair": {
    "criteria": {
      "has_the_recipe": "2023-12-29 11:19:36 +0100"
    },
    "done": true
  },
  "immersivepetroleum:recipes/immersivepetroleum/projector": {
    "criteria": {
      "has_the_recipe": "2023-12-29 11:19:36 +0100"
    },
    "done": true
  },
  "minecraft:recipes/tools/clock": {
    "criteria": {
      "has_redstone": "2023-12-29 11:26:50 +0100"
    },
    "done": true
  },
  "immersivepetroleum:recipes/building_blocks/weathered_cut_copper_stairs_paraffin_waxed": {
    "criteria": {
      "has_the_recipe": "2023-12-29 11:19:36 +0100"
    },
    "done": true
  },
  "mekanism:root": {
    "criteria": {
      "automatic": "2023-12-29 11:19:36 +0100"
    },
    "done": true
  },
  "immersivepetroleum:recipes/immersivepetroleum/auto_lubricator": {
    "criteria": {
      "has_the_recipe": "2023-12-29 11:19:36 +0100"
    },
    "done": true
  },
  "minecraft:recipes/redstone/redstone_block": {
    "criteria": {
      "has_redstone": "2023-12-29 11:26:50 +0100"
    },
    "done": true
  },
  "immersivepetroleum:recipes/immersivepetroleum/upgrade_paddles": {
    "criteria": {
      "has_the_recipe": "2023-12-29 11:19:36 +0100"
    },
    "done": true
  },
  "farmersdelight:recipes/farmersdelight/cooking/dog_food": {
    "criteria": {
      "has_any_ingredient": "2023-12-29 11:22:29 +0100"
    },
    "done": true
  },
  "minecraft:recipes/redstone/piston": {
    "criteria": {
      "has_redstone": "2023-12-29 11:26:50 +0100"
    },
    "done": true
  },
  "immersivepetroleum:recipes/immersivepetroleum/oil_can": {
    "criteria": {
      "has_the_recipe": "2023-12-29 11:19:36 +0100"
    },
    "done": true
  },
  "immersivepetroleum:recipes/immersivepetroleum/flarestack": {
    "criteria": {
      "has_the_recipe": "2023-12-29 11:19:36 +0100"
    },
    "done": true
  },
  "immersiveengineering:recipes/immersiveengineering/crafting/chute_steel": {
    "criteria": {
      "has_plate": "2023-12-29 11:26:42 +0100"
    },
    "done": true
  },
  "immersivepetroleum:recipes/building_blocks/oxidized_copper_paraffin_waxed": {
    "criteria": {
      "has_the_recipe": "2023-12-29 11:19:36 +0100"
    },
    "done": true
  },
  "immersivepetroleum:recipes/building_blocks/oxidized_cut_copper_paraffin_waxed": {
    "criteria": {
      "has_the_recipe": "2023-12-29 11:19:36 +0100"
    },
    "done": true
  },
  "immersivepetroleum:recipes/building_blocks/exposed_copper_paraffin_waxed": {
    "criteria": {
      "has_the_recipe": "2023-12-29 11:19:36 +0100"
    },
    "done": true
  },
  "alchemistry:recipes/dissolver/redstone_block": {
    "criteria": {
      "has_the_recipe": "2023-12-29 11:26:50 +0100"
    },
    "done": true
  },
  "immersivepetroleum:recipes/immersivepetroleum/molotov_wool": {
    "criteria": {
      "has_the_recipe": "2023-12-29 11:19:36 +0100"
    },
    "done": true
  },
  "immersivepetroleum:recipes/decorations/candle": {
    "criteria": {
      "has_the_recipe": "2023-12-29 11:19:36 +0100"
    },
    "done": true
  },
  "immersivepetroleum:recipes/immersivepetroleum/molotov_fabric": {
    "criteria": {
      "has_the_recipe": "2023-12-29 11:19:36 +0100"
    },
    "done": true
  },
  "immersivepetroleum:recipes/immersiveengineering/toolupgrade_drill_lube": {
    "criteria": {
      "has_the_recipe": "2023-12-29 11:19:36 +0100"
    },
    "done": true
  },
  "immersivepetroleum:recipes/immersivepetroleum/asphalt_slab": {
    "criteria": {
      "has_the_recipe": "2023-12-29 11:19:36 +0100"
    },
    "done": true
  },
  "minecraft:recipes/redstone/note_block": {
    "criteria": {
      "has_redstone": "2023-12-29 11:26:50 +0100"
    },
    "done": true
  },
  "immersiveengineering:recipes/immersiveengineering/crafting/armor_steel_head": {
    "criteria": {
      "has_steel_plate": "2023-12-29 11:26:42 +0100"
    },
    "done": true
  },
  "minecraft:recipes/redstone/dropper": {
    "criteria": {
      "has_redstone": "2023-12-29 11:26:50 +0100"
    },
    "done": true
  },
  "immersivepetroleum:recipes/immersivepetroleum/upgrade_reinforced_hull": {
    "criteria": {
      "has_the_recipe": "2023-12-29 11:19:36 +0100"
    },
    "done": true
  },
  "immersivepetroleum:recipes/immersiveengineering/ersatz_leather": {
    "criteria": {
      "has_the_recipe": "2023-12-29 11:19:36 +0100"
    },
    "done": true
  },
  "minecraft:recipes/building_blocks/bone_block": {
    "criteria": {
      "has_bone_meal": "2023-12-29 11:22:29 +0100"
    },
    "done": true
  },
  "immersivepetroleum:recipes/immersivepetroleum/upgrade_tank": {
    "criteria": {
      "has_the_recipe": "2023-12-29 11:19:36 +0100"
    },
    "done": true
  },
  "DataVersion": 3120
}